picard/__init__.py
picard/_core_picard.py
picard/_tools.py
picard/densities.py
picard/dropin_sklearn.py
picard/solver.py
python_picard-0.7.dist-info/LICENSE
python_picard-0.7.dist-info/METADATA
python_picard-0.7.dist-info/WHEEL
python_picard-0.7.dist-info/top_level.txt
python_picard-0.7.dist-info/RECORD
