Metadata-Version: 2.1
Name: python-picard
Version: 0.7
Summary: Preconditoned ICA for Real Data
Home-page: https://pierreablin.github.io/picard
Maintainer: Pierre Ablin
Maintainer-email: pierre.ablin@inria.fr
License: BSD (3-clause)
Download-URL: https://github.com/pierreablin/picard.git
Platform: any
Classifier: Intended Audience :: Science/Research
Classifier: Intended Audience :: Developers
Classifier: License :: OSI Approved
Classifier: Programming Language :: Python
Classifier: Topic :: Software Development
Classifier: Topic :: Scientific/Engineering
Classifier: Operating System :: Microsoft :: Windows
Classifier: Operating System :: POSIX
Classifier: Operating System :: Unix
Classifier: Operating System :: MacOS
Classifier: Programming Language :: Python :: 3
Requires-Python: >=3.7
License-File: LICENSE
